py_doc/__init__.py
py_doc/document.py
py_doc/image.py
py_doc/ocr.py
py_doc/pdf.py
py_doc/utils.py
py_doc/yolov7/__init__.py
py_doc/yolov7/detect.py
py_doc/yolov7/document_detection.py
py_doc/yolov7/export.py
py_doc/yolov7/hubconf.py
py_doc/yolov7/test.py
py_doc/yolov7/train.py
py_doc/yolov7/train_aux.py
py_doc/yolov7/models/__init__.py
py_doc/yolov7/models/common.py
py_doc/yolov7/models/experimental.py
py_doc/yolov7/models/yolo.py
py_doc/yolov7/utils/__init__.py
py_doc/yolov7/utils/activations.py
py_doc/yolov7/utils/add_nms.py
py_doc/yolov7/utils/autoanchor.py
py_doc/yolov7/utils/datasets.py
py_doc/yolov7/utils/general.py
py_doc/yolov7/utils/google_utils.py
py_doc/yolov7/utils/loss.py
py_doc/yolov7/utils/metrics.py
py_doc/yolov7/utils/plots.py
py_doc/yolov7/utils/torch_utils.py
py_doc/yolov7/utils/aws/__init__.py
py_doc/yolov7/utils/aws/resume.py
py_doc/yolov7/utils/wandb_logging/__init__.py
py_doc/yolov7/utils/wandb_logging/log_dataset.py
py_doc/yolov7/utils/wandb_logging/wandb_utils.py
py_doc/yolov7/weights/yolov7-tiny.pt
tests/__init__.py
tests/document_tests.py
tests/image_tests.py
tests/ocr_tests.py
tests/pdf_tests.py
py_doc-0.1.3.dist-info/METADATA
py_doc-0.1.3.dist-info/WHEEL
py_doc-0.1.3.dist-info/top_level.txt
py_doc-0.1.3.dist-info/RECORD
